CHANGELOG.md
README.md
__init__.py
mitol/__init__.py
mitol/authentication/__init__.py
mitol/authentication/apps.py
mitol/authentication/py.typed
mitol/authentication/migrations/__init__.py
mitol/authentication/serializers/__init__.py
mitol/authentication/serializers/djoser_serializers.py
mitol/authentication/settings/__init__.py
mitol/authentication/settings/djoser_settings.py
mitol/authentication/settings/touchstone.py
mitol/authentication/urls/__init__.py
mitol/authentication/urls/djoser_urls.py
mitol/authentication/urls/saml.py
mitol/authentication/views/__init__.py
mitol/authentication/views/djoser_views.py
mitol/authentication/views/saml.py
mitol_django_authentication-2025.3.17.dist-info/METADATA
mitol_django_authentication-2025.3.17.dist-info/WHEEL
mitol_django_authentication-2025.3.17.dist-info/RECORD
